CryptoClasec/__init__.py
CryptoClasec/caesar.py
CryptoClasec/hillcipher.py
CryptoClasec/monoalphabetic.py
CryptoClasec/playfair.py
CryptoClasec/vernam.py
CryptoClasec/vigenere.py
CryptoClasec-1.0.2.dist-info/LICENSE
CryptoClasec-1.0.2.dist-info/METADATA
CryptoClasec-1.0.2.dist-info/WHEEL
CryptoClasec-1.0.2.dist-info/top_level.txt
CryptoClasec-1.0.2.dist-info/RECORD
