Metadata-Version: 2.1
Name: CryptoClasec
Version: 1.0.2
Summary: A library for various cryptography algorithms (Caesar, Hill Cipher.)
Home-page: https://github.com/hemaabokila/CryptoClasec
Author: Ibrahem Abo kila
Author-email: ibrahemabokila@gmail.com
Classifier: Programming Language :: Python :: 3
Classifier: License :: OSI Approved :: MIT License
Classifier: Operating System :: OS Independent
Requires-Python: >=3.6
License-File: LICENSE
